aiogram_djpersistence/__init__.py
aiogram_djpersistence/admin.py
aiogram_djpersistence/apps.py
aiogram_djpersistence/migrations/0001_initial.py
aiogram_djpersistence/migrations/__init__.py
aiogram_djpersistence/models.py
aiogram_djpersistence/storage.py
python_telegram_bot_django_persistence/__init__.py
python_telegram_bot_django_persistence/admin.py
python_telegram_bot_django_persistence/apps.py
python_telegram_bot_django_persistence/migrations/0001_initial.py
python_telegram_bot_django_persistence/migrations/0002_alter_conversationdata_state.py
python_telegram_bot_django_persistence/migrations/0003_alter_userdata_user_id.py
python_telegram_bot_django_persistence/migrations/__init__.py
python_telegram_bot_django_persistence/models.py
python_telegram_bot_django_persistence/persistence.py
python_telegram_bot_django_persistence-0.2.1.dist-info/LICENSE
python_telegram_bot_django_persistence-0.2.1.dist-info/METADATA
python_telegram_bot_django_persistence-0.2.1.dist-info/WHEEL
python_telegram_bot_django_persistence-0.2.1.dist-info/RECORD
