Metadata-Version: 2.1
Name: python-telegram-bot-django-persistence
Version: 0.2.1
Summary: Package to use Django ORM as persistence engine in Python Telegram Bot
Home-page: https://github.com/GamePad64/python-telegram-bot-django-persistence
License: MIT
Author: Alexander Shishenko
Author-email: alex@shishenko.com
Requires-Python: >=3.10,<4.0
Classifier: Framework :: Django :: 5.0
Classifier: Framework :: Django :: 5.1
Classifier: Intended Audience :: Developers
Classifier: License :: OSI Approved :: MIT License
Classifier: Programming Language :: Python :: 3
Classifier: Programming Language :: Python :: 3.10
Classifier: Programming Language :: Python :: 3.11
Classifier: Programming Language :: Python :: 3.12
Classifier: Programming Language :: Python :: 3.13
Classifier: Topic :: Internet
Requires-Dist: Django (>=5.0)
Requires-Dist: django-stubs (>=5.0.4,<6.0.0)
